raggen/__init__.py
raggen/raggen.py
raggen/splitter.py
raggen/templates/meta_embed
raggen-0.1.1.dist-info/METADATA
raggen-0.1.1.dist-info/WHEEL
raggen-0.1.1.dist-info/licenses/LICENSE
raggen-0.1.1.dist-info/RECORD
