Metadata-Version: 2.4
Name: raggen
Version: 0.1.1
Summary: RAG dataset generator
Project-URL: Homepage, https://github.com/alex-karev/birbtalk
Project-URL: Issues, https://github.com/alex-karev/birbtalk/issues
Author-email: Alex Karev <karev.as99@gmail.com>
License:                                  Apache License
License-File: LICENSE
Classifier: Operating System :: OS Independent
Classifier: Programming Language :: Python :: 3
Requires-Python: >=3.10
Requires-Dist: html2text==2024.2.26
Requires-Dist: jinja2==3.1.5
Requires-Dist: langchain-text-splitters==0.3.6
Requires-Dist: langchain[openai]==0.3.18
Requires-Dist: mammoth==1.9.0
Requires-Dist: marker-pdf==1.3.5
Requires-Dist: pandas==2.2.3
Requires-Dist: pydantic==2.10.6
Requires-Dist: tenacity==9.0.0
Requires-Dist: tiktoken==0.8.0
Requires-Dist: tqdm==4.67.1
